{
    "type": "DashboardV2SyncDefinition",
    "name": "Credits Estimator Using Data Volume - CSE Version",
    "description": "",
    "title": "Credits Estimator Using Data Volume - CSE Version",
    "rootPanel": null,
    "theme": "Light",
    "topologyLabelMap": {
        "data": {}
    },
    "refreshInterval": 0,
    "timeRange": {
        "type": "BeginBoundedTimeRange",
        "from": {
            "type": "RelativeTimeRangeBoundary",
            "relativeTime": "-1w"
        },
        "to": null
    },
    "layout": {
        "layoutType": "Grid",
        "layoutStructures": [
            {
                "key": "panelPANE-2F6D26D09EBDFA44",
                "structure": "{\"height\":9,\"width\":12,\"x\":12,\"y\":14}"
            },
            {
                "key": "panelBCE5CC709022B84C",
                "structure": "{\"height\":8,\"width\":6,\"x\":0,\"y\":42}"
            },
            {
                "key": "panelA46D36779F877B4E",
                "structure": "{\"height\":8,\"width\":6,\"x\":6,\"y\":42}"
            },
            {
                "key": "panel968E0544AE1EF947",
                "structure": "{\"height\":8,\"width\":6,\"x\":12,\"y\":42}"
            },
            {
                "key": "panelE64C346DA44AA847",
                "structure": "{\"height\":9,\"width\":12,\"x\":0,\"y\":14}"
            },
            {
                "key": "panelPANE-D51893298F18B845",
                "structure": "{\"height\":8,\"width\":24,\"x\":0,\"y\":60}"
            },
            {
                "key": "panel807969999E849A42",
                "structure": "{\"height\":6,\"width\":5,\"x\":0,\"y\":8}"
            },
            {
                "key": "panelPANE-12972226BA631B46",
                "structure": "{\"height\":7,\"width\":8,\"x\":0,\"y\":0}"
            },
            {
                "key": "panel5BC87A89911A8B42",
                "structure": "{\"height\":1,\"width\":24,\"x\":0,\"y\":41}"
            },
            {
                "key": "panel4E8CBEF5843F984B",
                "structure": "{\"height\":1,\"width\":24,\"x\":0,\"y\":59}"
            },
            {
                "key": "panel4B4C173A89EC8945",
                "structure": "{\"height\":8,\"width\":8,\"x\":0,\"y\":24}"
            },
            {
                "key": "panel0990DD519B4BEA49",
                "structure": "{\"height\":8,\"width\":8,\"x\":8,\"y\":24}"
            },
            {
                "key": "panel54C7C34EB4D68949",
                "structure": "{\"height\":8,\"width\":8,\"x\":16,\"y\":24}"
            },
            {
                "key": "panel53A98BB8870DE848",
                "structure": "{\"height\":1,\"width\":24,\"x\":0,\"y\":23}"
            },
            {
                "key": "panel774314BABF501943",
                "structure": "{\"height\":1,\"width\":24,\"x\":0,\"y\":32}"
            },
            {
                "key": "panel32BB8380A63E9B41",
                "structure": "{\"height\":8,\"width\":16,\"x\":0,\"y\":33}"
            },
            {
                "key": "panel013E0607B2E87A41",
                "structure": "{\"height\":8,\"width\":8,\"x\":16,\"y\":33}"
            },
            {
                "key": "panel2E9ED2749604AA4E",
                "structure": "{\"height\":1,\"width\":24,\"x\":0,\"y\":7}"
            },
            {
                "key": "panel2527AC6BBD9AF842",
                "structure": "{\"height\":4,\"width\":16,\"x\":0,\"y\":50}"
            },
            {
                "key": "panel323647DE98CB5B4A",
                "structure": "{\"height\":5,\"width\":16,\"x\":0,\"y\":54}"
            },
            {
                "key": "panelABC5F685A294E94D",
                "structure": "{\"height\":9,\"width\":8,\"x\":16,\"y\":50}"
            },
            {
                "key": "panelB0AACB67902B884D",
                "structure": "{\"height\":6,\"width\":19,\"x\":5,\"y\":8}"
            },
            {
                "key": "panelFD4EFA759646AB4C",
                "structure": "{\"height\":4,\"width\":3,\"x\":14,\"y\":3}"
            },
            {
                "key": "panel01F2578696E9D944",
                "structure": "{\"height\":4,\"width\":3,\"x\":8,\"y\":3}"
            },
            {
                "key": "panel668ACBF792B57842",
                "structure": "{\"height\":4,\"width\":3,\"x\":11,\"y\":3}"
            },
            {
                "key": "panel0F0DA71B810C494A",
                "structure": "{\"height\":4,\"width\":7,\"x\":17,\"y\":3}"
            },
            {
                "key": "panelB6F0E7878F04384E",
                "structure": "{\"height\":3,\"width\":9,\"x\":8,\"y\":0}"
            },
            {
                "key": "panelAFB174FABBC89B4D",
                "structure": "{\"height\":3,\"width\":7,\"x\":17,\"y\":0}"
            },
            {
                "key": "panelF2060CD3BDA43842",
                "structure": "{\"height\":8,\"width\":6,\"x\":18,\"y\":42}"
            }
        ]
    },
    "panels": [
        {
            "id": null,
            "key": "panelPANE-2F6D26D09EBDFA44",
            "title": "Ingest By Tier (GB)",
            "visualSettings": "{\"title\":{\"fontSize\":16},\"general\":{\"type\":\"column\",\"displayType\":\"stacked\",\"fillOpacity\":1,\"mode\":\"timeSeries\"},\"axes\":{\"axisX\":{\"showLabels\":true,\"title\":\"\",\"titleFontSize\":11,\"labelFontSize\":10},\"axisY\":{\"showLabels\":true,\"title\":\"\",\"titleFontSize\":11,\"labelFontSize\":12,\"logarithmic\":false,\"gridColor\":\"#dde4e9\",\"unit\":{\"value\":\"GB\",\"isCustom\":false}}},\"legend\":{\"enabled\":true,\"verticalAlign\":\"bottom\",\"fontSize\":12,\"maxHeight\":50,\"showAsTable\":false,\"wrap\":true},\"color\":{\"family\":\"scheme9\"},\"overrides\":[],\"series\":{}}",
            "keepVisualSettingsConsistentWithParent": true,
            "panelType": "SumoSearchPanel",
            "queries": [
                {
                    "queryString": "_index=sumologic_volume sizeInBytes \n_sourceCategory=view_volume\n\n| parse regex \"\\\"(?<view>[^\\\"]+)\\\"\\:\\{\\\"sizeInBytes\\\"\\:(?<bytes>\\d+),\\\"count\\\"\\:(?<count>\\d+)\\}\" multi\n\n| if(view matches \"_sumologic_report*\",\"saved_views\",view) as view\n//| if(view matches \"*volume*\",\"internal\",view) as view\n| timeslice by {{timeslice}} \n\n| sum(bytes) as size_in_bytes by view,_timeslice\n| size_in_bytes / 1024 / 1024 / 1024 as gbytes\n//| concat(deployment,\"_\",org_id) as key\n//| lookup org_id,org_name,daily_gb_limit from /shared/lookups/master_orgs on key=key  \n| sum(gbytes) as gbytes by view,_timeslice\n| sum(gbytes) as gbytes by view,_timeslice\n| \"continuous\" as tier\n| if(view matches /{{freq_regex}}/,\"frequent\",tier) as tier\n| if(view matches /{{infreq_regex}}/,\"infrequent\",tier) as tier\n| if (view matches /(?)CSE_[RS][ei]/,\"cse_data\",tier) as tier\n\n| 20 as cr_cont\n| 25 as cr_cse\n| 9 as cr_freq\n| 0.4 as cr_infreq\n| if (tier = \"continuous\",gbytes * ((100 - {{cse_pct}})  /100),0) as continuous\n| if (tier = \"continuous\",gbytes * ({{cse_pct}}  /100),0) as cse\n| if (tier = \"frequent\",gbytes,0) as frequent\n| if (tier = \"infrequent\",gbytes,0) as infrequent\n\n| concat(\"continuous:\",continuous,\"cse:\",cse,\"frequent:\",frequent,\"infrequent:\",infrequent) as transport\n| parse regex field = transport \"(?<type>[a-z_]+):(?<gbytes>[0-9]+)\" multi\n\n|  sum(gbytes) by type, _timeslice | transpose row _timeslice column type\n",
                    "queryType": "Logs",
                    "queryKey": "A",
                    "metricsQueryMode": null,
                    "metricsQueryData": null,
                    "tracesQueryData": null,
                    "parseMode": "Manual",
                    "timeSource": "Message"
                }
            ],
            "description": "",
            "timeRange": null,
            "coloringRules": null,
            "linkedDashboards": []
        },
        {
            "id": null,
            "key": "panelBCE5CC709022B84C",
            "title": "Continuous Partitions (GB)",
            "visualSettings": "{\"title\":{\"fontSize\":16},\"general\":{\"type\":\"column\",\"displayType\":\"stacked\",\"fillOpacity\":1,\"mode\":\"timeSeries\"},\"axes\":{\"axisX\":{\"showLabels\":true,\"title\":\"\",\"titleFontSize\":11,\"labelFontSize\":10},\"axisY\":{\"showLabels\":true,\"title\":\"\",\"titleFontSize\":11,\"labelFontSize\":12,\"logarithmic\":false,\"gridColor\":\"#dde4e9\"}},\"legend\":{\"enabled\":true,\"verticalAlign\":\"bottom\",\"fontSize\":12,\"maxHeight\":50,\"showAsTable\":false,\"wrap\":true},\"color\":{\"family\":\"scheme9\"},\"overrides\":[],\"series\":{}}",
            "keepVisualSettingsConsistentWithParent": true,
            "panelType": "SumoSearchPanel",
            "queries": [
                {
                    "queryString": "_index=sumologic_volume sizeInBytes \n_sourceCategory=view_volume\n\n| parse regex \"\\\"(?<view>[^\\\"]+)\\\"\\:\\{\\\"sizeInBytes\\\"\\:(?<bytes>\\d+),\\\"count\\\"\\:(?<count>\\d+)\\}\" multi\n\n| if(view matches \"_sumologic_report*\",\"saved_views\",view) as view\n//| if(view matches \"*volume*\",\"internal\",view) as view\n| timeslice by {{timeslice}} \n\n| sum(bytes) as size_in_bytes by view,_timeslice\n| size_in_bytes / 1024 / 1024 / 1024 as gbytes \n| sum(gbytes) as gbytes by view,_timeslice\n\n| \"continuous\" as tier\n| if(view matches /{{freq_regex}}/,\"frequent\",tier) as tier\n| if(view matches /{{infreq_regex}}/,\"infrequent\",tier) as tier\n| if (view matches /(?)CSE_[RS][ei]/,\"cse_data\",tier) as tier\n\n| where tier = \"continuous\"\n| view as index\n| if (index matches \"*sumologic*\",\"sumologic_internal\",index) as index\n|  sum(gbytes) as gbytes by index,_timeslice\n| transpose row _timeslice column index\n",
                    "queryType": "Logs",
                    "queryKey": "A",
                    "metricsQueryMode": null,
                    "metricsQueryData": null,
                    "tracesQueryData": null,
                    "parseMode": "Manual",
                    "timeSource": "Message"
                }
            ],
            "description": "",
            "timeRange": null,
            "coloringRules": null,
            "linkedDashboards": []
        },
        {
            "id": null,
            "key": "panelA46D36779F877B4E",
            "title": "Frequent Partitions (GB)",
            "visualSettings": "{\"title\":{\"fontSize\":16},\"general\":{\"type\":\"column\",\"displayType\":\"stacked\",\"fillOpacity\":1,\"mode\":\"timeSeries\"},\"axes\":{\"axisX\":{\"showLabels\":true,\"title\":\"\",\"titleFontSize\":11,\"labelFontSize\":10},\"axisY\":{\"showLabels\":true,\"title\":\"\",\"titleFontSize\":11,\"labelFontSize\":12,\"logarithmic\":false,\"gridColor\":\"#dde4e9\"}},\"legend\":{\"enabled\":true,\"verticalAlign\":\"bottom\",\"fontSize\":12,\"maxHeight\":50,\"showAsTable\":false,\"wrap\":true},\"color\":{\"family\":\"scheme9\"},\"overrides\":[],\"series\":{}}",
            "keepVisualSettingsConsistentWithParent": true,
            "panelType": "SumoSearchPanel",
            "queries": [
                {
                    "queryString": "_index=sumologic_volume sizeInBytes \n_sourceCategory=view_volume\n\n| parse regex \"\\\"(?<view>[^\\\"]+)\\\"\\:\\{\\\"sizeInBytes\\\"\\:(?<bytes>\\d+),\\\"count\\\"\\:(?<count>\\d+)\\}\" multi\n\n| if(view matches \"_sumologic_report*\",\"saved_views\",view) as view\n//| if(view matches \"*volume*\",\"internal\",view) as view\n| timeslice by {{timeslice}} \n\n| sum(bytes) as size_in_bytes by view,_timeslice\n| size_in_bytes / 1024 / 1024 / 1024 as gbytes\n| sum(gbytes) as gbytes by view,_timeslice\n\n| \"continuous\" as tier\n| if(view matches /{{freq_regex}}/,\"frequent\",tier) as tier\n| if(view matches /{{infreq_regex}}/,\"infrequent\",tier) as tier\n| if (view matches /(?)CSE_[RS][ei]/,\"cse_data\",tier) as tier\n\n| where tier = \"frequent\"\n| view as index\n| if (index matches \"*sumologic*\",\"sumologic_internal\",index) as index\n|  sum(gbytes) as gbytes by index,_timeslice\n| transpose row _timeslice column index\n",
                    "queryType": "Logs",
                    "queryKey": "A",
                    "metricsQueryMode": null,
                    "metricsQueryData": null,
                    "tracesQueryData": null,
                    "parseMode": "Manual",
                    "timeSource": "Message"
                }
            ],
            "description": "",
            "timeRange": null,
            "coloringRules": null,
            "linkedDashboards": []
        },
        {
            "id": null,
            "key": "panel968E0544AE1EF947",
            "title": "InFrequent Partitions (GB)",
            "visualSettings": "{\"title\":{\"fontSize\":16},\"general\":{\"type\":\"column\",\"displayType\":\"stacked\",\"fillOpacity\":1,\"mode\":\"timeSeries\"},\"axes\":{\"axisX\":{\"showLabels\":true,\"title\":\"\",\"titleFontSize\":11,\"labelFontSize\":10},\"axisY\":{\"showLabels\":true,\"title\":\"\",\"titleFontSize\":11,\"labelFontSize\":12,\"logarithmic\":false,\"gridColor\":\"#dde4e9\"}},\"legend\":{\"enabled\":true,\"verticalAlign\":\"bottom\",\"fontSize\":12,\"maxHeight\":50,\"showAsTable\":false,\"wrap\":true},\"color\":{\"family\":\"scheme9\"},\"overrides\":[],\"series\":{}}",
            "keepVisualSettingsConsistentWithParent": true,
            "panelType": "SumoSearchPanel",
            "queries": [
                {
                    "queryString": "_index=sumologic_volume sizeInBytes \n_sourceCategory=view_volume\n\n| parse regex \"\\\"(?<view>[^\\\"]+)\\\"\\:\\{\\\"sizeInBytes\\\"\\:(?<bytes>\\d+),\\\"count\\\"\\:(?<count>\\d+)\\}\" multi\n\n| if(view matches \"_sumologic_report*\",\"saved_views\",view) as view\n//| if(view matches \"*volume*\",\"internal\",view) as view\n| timeslice by {{timeslice}} \n\n| sum(bytes) as size_in_bytes by view,_timeslice\n| size_in_bytes / 1024 / 1024 / 1024 as gbytes\n| sum(gbytes) as gbytes by view,_timeslice\n\n| \"continuous\" as tier\n| if(view matches /{{freq_regex}}/,\"frequent\",tier) as tier\n| if(view matches /{{infreq_regex}}/,\"infrequent\",tier) as tier\n| if (view matches /(?)CSE_[RS][ei]/,\"cse_data\",tier) as tier\n\n| where tier = \"infrequent\"\n| view as index\n| if (index matches \"*sumologic*\",\"sumologic_internal\",index) as index\n|  sum(gbytes) as gbytes by index,_timeslice\n| transpose row _timeslice column index\n",
                    "queryType": "Logs",
                    "queryKey": "A",
                    "metricsQueryMode": null,
                    "metricsQueryData": null,
                    "tracesQueryData": null,
                    "parseMode": "Manual",
                    "timeSource": "Message"
                }
            ],
            "description": "",
            "timeRange": null,
            "coloringRules": null,
            "linkedDashboards": []
        },
        {
            "id": null,
            "key": "panelE64C346DA44AA847",
            "title": "Ingestion Credit Estimate (Credits)",
            "visualSettings": "{\"title\":{\"fontSize\":14},\"general\":{\"type\":\"column\",\"displayType\":\"stacked\",\"fillOpacity\":1,\"mode\":\"timeSeries\"},\"axes\":{\"axisX\":{\"title\":\"\",\"titleFontSize\":12,\"labelFontSize\":12},\"axisY\":{\"title\":\"\",\"titleFontSize\":12,\"labelFontSize\":12,\"logarithmic\":false}},\"legend\":{\"enabled\":true,\"verticalAlign\":\"bottom\",\"fontSize\":12,\"maxHeight\":50,\"showAsTable\":false,\"wrap\":true},\"color\":{\"family\":\"Categorical Default\"},\"overrides\":[],\"series\":{}}",
            "keepVisualSettingsConsistentWithParent": true,
            "panelType": "SumoSearchPanel",
            "queries": [
                {
                    "queryString": "_index=sumologic_volume sizeInBytes \n_sourceCategory=view_volume\n\n| parse regex \"\\\"(?<view>[^\\\"]+)\\\"\\:\\{\\\"sizeInBytes\\\"\\:(?<bytes>\\d+),\\\"count\\\"\\:(?<count>\\d+)\\}\" multi\n\n| if(view matches \"_sumologic_report*\",\"saved_views\",view) as view\n//| if(view matches \"*volume*\",\"internal\",view) as view\n| timeslice by {{timeslice}} \n\n| sum(bytes) as size_in_bytes by view,_timeslice\n| size_in_bytes / 1024 / 1024 / 1024 as gbytes\n\n| sum(gbytes) as gbytes by view,_timeslice\n| \"continuous\" as tier\n| if(view matches /{{freq_regex}}/,\"frequent\",tier) as tier\n| if(view matches /{{infreq_regex}}/,\"infrequent\",tier) as tier\n| if (view matches /(?)CSE_[RS][ei]/,\"cse_data\",tier) as tier\n\n| 20 as cr_cont\n| 25 as cr_cse\n| 9 as cr_freq\n| 0.4 as cr_infreq\n| if (tier = \"continuous\",cr_cont * gbytes * ((100 - {{cse_pct}})  /100),0) as cr_continuous\n| if (tier = \"continuous\",cr_cse * gbytes * ({{cse_pct}}  /100),0) as cr_cse\n| if (tier = \"frequent\",cr_freq * gbytes,0) as cr_frequent\n| if (tier = \"infrequent\",cr_infreq * gbytes,0) as cr_infrequent\n\n| concat(\"cr_continuous:\",cr_continuous,\"cr_cse:\",cr_cse,\"cr_frequent:\",cr_frequent,\"cr_infrequent:\",cr_infrequent) as transport\n| parse regex field = transport \"(?<type>[a-z_]+):(?<credits>[0-9]+)\" multi\n\n|  sum(credits) by type, _timeslice | transpose row _timeslice column type\n",
                    "queryType": "Logs",
                    "queryKey": "A",
                    "metricsQueryMode": null,
                    "metricsQueryData": null,
                    "tracesQueryData": null,
                    "parseMode": "Manual",
                    "timeSource": "Message"
                }
            ],
            "description": "",
            "timeRange": null,
            "coloringRules": null,
            "linkedDashboards": []
        },
        {
            "id": null,
            "key": "panelPANE-D51893298F18B845",
            "title": "Partition Mappings",
            "visualSettings": "{\"title\":{\"fontSize\":16},\"general\":{\"type\":\"table\",\"displayType\":\"default\",\"paginationPageSize\":100,\"fontSize\":12,\"mode\":\"distribution\",\"decimals\":1},\"series\":{}}",
            "keepVisualSettingsConsistentWithParent": true,
            "panelType": "SumoSearchPanel",
            "queries": [
                {
                    "queryString": "_index=sumologic_volume sizeInBytes \n_sourceCategory=view_volume\n\n| parse regex \"\\\"(?<view>[^\\\"]+)\\\"\\:\\{\\\"sizeInBytes\\\"\\:(?<bytes>\\d+),\\\"count\\\"\\:(?<count>\\d+)\\}\" multi\n\n| sum(bytes) as size_in_bytes by view\n| size_in_bytes / 1024 / 1024 / 1024 as gbytes\n| sum(gbytes) as gbytes by view\n\n| \"continuous\" as tier\n| if(view matches /{{freq_regex}}/,\"frequent\",tier) as tier\n| if(view matches /{{infreq_regex}}/,\"infrequent\",tier) as tier\n| if (view matches /(?)CSE_[RS][ei]/,\"cse_data\",tier) as tier\n| view as rename_for_report\n| if(view matches \"_sumologic_report*\",\"saved_views\",view) as rename_for_report\n| if (view matches \"*sumologic*\",\"sumologic_internal\",rename_for_report) as rename_for_report\n| 20 as cr_cont\n| 9 as cr_freq\n| 0.4 as cr_infreq\n| if (tier = \"continuous\",cr_cont * gbytes,0) as ingest_credits_consumed\n| if (tier = \"frequent\",cr_freq * gbytes,ingest_credits_consumed) as ingest_credits_consumed\n| if (tier = \"infrequent\",cr_infreq * gbytes,ingest_credits_consumed) as ingest_credits_consumed\n| gbytes as gbytes\n| sort ingest_credits_consumed\n| fields -cr_cont,cr_freq,cr_infreq\n| ingest_credits_consumed / gbytes as CPGI ",
                    "queryType": "Logs",
                    "queryKey": "A",
                    "metricsQueryMode": null,
                    "metricsQueryData": null,
                    "tracesQueryData": null,
                    "parseMode": "Manual",
                    "timeSource": "Message"
                }
            ],
            "description": "",
            "timeRange": null,
            "coloringRules": null,
            "linkedDashboards": []
        },
        {
            "id": null,
            "key": "panel807969999E849A42",
            "title": "Ingest Credits By Type",
            "visualSettings": "{\"title\":{\"fontSize\":14},\"general\":{\"type\":\"pie\",\"displayType\":\"default\",\"fillOpacity\":1,\"startAngle\":270,\"innerRadius\":\"30%\",\"maxNumOfSlices\":10,\"mode\":\"distribution\"},\"axes\":{\"axisX\":{\"titleFontSize\":12,\"labelFontSize\":12},\"axisY\":{\"titleFontSize\":12,\"labelFontSize\":12}},\"overrides\":[],\"series\":{}}",
            "keepVisualSettingsConsistentWithParent": true,
            "panelType": "SumoSearchPanel",
            "queries": [
                {
                    "queryString": "_index=sumologic_volume sizeInBytes \n_sourceCategory=view_volume\n\n| parse regex \"\\\"(?<view>[^\\\"]+)\\\"\\:\\{\\\"sizeInBytes\\\"\\:(?<bytes>\\d+),\\\"count\\\"\\:(?<count>\\d+)\\}\" multi\n\n| if(view matches \"_sumologic_report*\",\"saved_views\",view) as view\n//| if(view matches \"*volume*\",\"internal\",view) as view\n| timeslice by {{timeslice}} \n\n| sum(bytes) as size_in_bytes by view,_timeslice\n| size_in_bytes / 1024 / 1024 / 1024 as gbytes\n\n| sum(gbytes) as gbytes by view,_timeslice\n| \"continuous\" as tier\n| if(view matches /{{freq_regex}}/,\"frequent\",tier) as tier\n| if(view matches /{{infreq_regex}}/,\"infrequent\",tier) as tier\n| if (view matches /(?)CSE_[RS][ei]/,\"cse_data\",tier) as tier\n\n| 20 as cr_cont\n| 25 as cr_cse\n| 9 as cr_freq\n| 0.4 as cr_infreq\n| if (tier = \"continuous\",cr_cont * gbytes * ((100 - {{cse_pct}})  /100),0) as cr_continuous\n| if (tier = \"continuous\",cr_cse * gbytes * ({{cse_pct}}  /100),0) as cr_cse\n| if (tier = \"frequent\",cr_freq * gbytes,0) as cr_frequent\n| if (tier = \"infrequent\",cr_infreq * gbytes,0) as cr_infrequent\n\n| concat(\"cr_continuous:\",cr_continuous,\"cr_cse:\",cr_cse,\"cr_frequent:\",cr_frequent,\"cr_infrequent:\",cr_infrequent) as transport\n| parse regex field = transport \"(?<type>[a-z_]+):(?<credits>[0-9]+)\" multi\n| sum(credits) as credits by type\n",
                    "queryType": "Logs",
                    "queryKey": "A",
                    "metricsQueryMode": null,
                    "metricsQueryData": null,
                    "tracesQueryData": null,
                    "parseMode": "Manual",
                    "timeSource": "Message"
                }
            ],
            "description": "",
            "timeRange": null,
            "coloringRules": null,
            "linkedDashboards": []
        },
        {
            "id": null,
            "key": "panelPANE-12972226BA631B46",
            "title": "About",
            "visualSettings": "{\"general\":{\"mode\":\"TextPanel\",\"type\":\"text\",\"displayType\":\"default\"},\"title\":{\"fontSize\":16},\"series\":{},\"text\":{\"format\":\"markdown\",\"fontSize\":12}}",
            "keepVisualSettingsConsistentWithParent": true,
            "panelType": "TextPanel",
            "text": "This dashboard estimates INGEST , METRIC, STORAGE and INFREQUENT SCAN credits.\n\n**Log Ingest Credits** estimates require that regular expressions **must match** your partition to the correct tier.\n\n- Use params:```infreq_regex```  ```freq_regex``` ```cse_regex``` \n- cse_regex maps normalised cse_data partitions to exclude from ingest credits.\n\n**cse_pct** we can only estimate cse vs continous credits. Use the panel: 'CIP vs CSE Credits Estimate' to estimate a correct percent value for cse logs: ```_siemforward=true```\n\n**Infrequent Scan Credits**:\nFor infrequent scans data uses search audit infrequent search events. For more detailed infrequent scan dashboards see the [Infrequent App](https://help.sumologic.com/07Sumo-Logic-Apps/26Apps_for_Sumo/Infrequent_Data_Tier/Install_the_Infrequent_Data_Tier_App_and_view_the_Dashboards)\n\n**Storage Credits**\nWe can only estimate credits at full retention using recent ingest volume. You can set a retention period with ```average_retention_days``` parameter.\n\n**debug panel for log mappings** Use the log mapping panel at the bottom of the dashboard to verify partition to tier mapping."
        },
        {
            "id": null,
            "key": "panel5BC87A89911A8B42",
            "title": "GB Ingest By Partition",
            "visualSettings": "{\"general\":{\"mode\":\"TextPanel\",\"type\":\"text\",\"displayType\":\"default\"},\"title\":{\"fontSize\":16},\"series\":{},\"text\":{\"format\":\"text\"}}",
            "keepVisualSettingsConsistentWithParent": true,
            "panelType": "TextPanel",
            "text": "This panel uses"
        },
        {
            "id": null,
            "key": "panel4E8CBEF5843F984B",
            "title": "Detail / Regex Param Debug Report - Ingest Credits Per Partition",
            "visualSettings": "{\"general\":{\"mode\":\"TextPanel\",\"type\":\"text\",\"displayType\":\"default\"},\"title\":{\"fontSize\":16},\"series\":{},\"text\":{\"format\":\"text\"}}",
            "keepVisualSettingsConsistentWithParent": true,
            "panelType": "TextPanel",
            "text": "This panel uses"
        },
        {
            "id": null,
            "key": "panel4B4C173A89EC8945",
            "title": "Metric Ingest DPM Rate",
            "visualSettings": "{\"title\":{\"fontSize\":14},\"general\":{\"type\":\"column\",\"displayType\":\"stacked\",\"fillOpacity\":1,\"mode\":\"timeSeries\"},\"axes\":{\"axisX\":{\"title\":\"\",\"titleFontSize\":12,\"labelFontSize\":12},\"axisY\":{\"title\":\"\",\"titleFontSize\":12,\"labelFontSize\":12,\"logarithmic\":false}},\"legend\":{\"enabled\":true,\"verticalAlign\":\"bottom\",\"fontSize\":12,\"maxHeight\":50,\"showAsTable\":false,\"wrap\":true},\"color\":{\"family\":\"Categorical Default\"},\"overrides\":[],\"series\":{}}",
            "keepVisualSettingsConsistentWithParent": true,
            "panelType": "SumoSearchPanel",
            "queries": [
                {
                    "queryString": "_index=sumologic_volume dataPoints\n| where _sourceCategory=\"sourcecategory_metrics_volume\"\n| parse regex \"\\\"(?<sourcecategory>[^\\\"]+)\\\"\\:\\{\\\"dataPoints\\\"\\:(?<datapoints>\\d+)\\}\" multi\n| timeslice by {{timeslice}}\n|min(_messagetime) as f, max(_messagetime) as l , sum(datapoints) as datapoints by _timeslice, sourcecategory\n| ((l - f)/(1000*60)) as duration_in_min\n| datapoints / duration_in_min as %\"DPM\" \n| fields _timeslice, dpm, sourcecategory\n| transpose row _timeslice column sourcecategory",
                    "queryType": "Logs",
                    "queryKey": "A",
                    "metricsQueryMode": null,
                    "metricsQueryData": null,
                    "tracesQueryData": null,
                    "parseMode": "Manual",
                    "timeSource": "Message"
                }
            ],
            "description": "",
            "timeRange": null,
            "coloringRules": null,
            "linkedDashboards": []
        },
        {
            "id": null,
            "key": "panel0990DD519B4BEA49",
            "title": "Metric Ingest Credits",
            "visualSettings": "{\"title\":{\"fontSize\":14},\"general\":{\"type\":\"column\",\"displayType\":\"stacked\",\"fillOpacity\":1,\"mode\":\"timeSeries\"},\"axes\":{\"axisX\":{\"title\":\"\",\"titleFontSize\":12,\"labelFontSize\":12},\"axisY\":{\"title\":\"\",\"titleFontSize\":12,\"labelFontSize\":12,\"logarithmic\":false}},\"legend\":{\"enabled\":true,\"verticalAlign\":\"bottom\",\"fontSize\":12,\"maxHeight\":50,\"showAsTable\":false,\"wrap\":true},\"color\":{\"family\":\"Categorical Default\"},\"overrides\":[],\"series\":{}}",
            "keepVisualSettingsConsistentWithParent": true,
            "panelType": "SumoSearchPanel",
            "queries": [
                {
                    "queryString": "_index=sumologic_volume dataPoints\n| where _sourceCategory=\"sourcecategory_metrics_volume\"\n| parse regex \"\\\"(?<sourcecategory>[^\\\"]+)\\\"\\:\\{\\\"dataPoints\\\"\\:(?<datapoints>\\d+)\\}\" multi\n| timeslice by {{timeslice}}\n|min(_messagetime) as f, max(_messagetime) as l , sum(datapoints) as datapoints by _timeslice,sourcecategory\n| ((l - f)/(1000*60)) as duration_in_min\n| datapoints / duration_in_min as dpm\n| (dpm)/1000  * 3 * ( duration_in_min / ( 60 * 24))  as cr_metrics\n| fields _timeslice, cr_metrics,sourcecategory\n| transpose row _timeslice column sourcecategory",
                    "queryType": "Logs",
                    "queryKey": "A",
                    "metricsQueryMode": null,
                    "metricsQueryData": null,
                    "tracesQueryData": null,
                    "parseMode": "Manual",
                    "timeSource": "Message"
                }
            ],
            "description": "",
            "timeRange": null,
            "coloringRules": null,
            "linkedDashboards": []
        },
        {
            "id": null,
            "key": "panel54C7C34EB4D68949",
            "title": "Metric Ingest Credits Consumed",
            "visualSettings": "{\"title\":{\"fontSize\":16},\"general\":{\"type\":\"svp\",\"displayType\":\"default\",\"mode\":\"singleValueMetrics\"},\"svp\":{\"option\":\"Average\",\"label\":\"Credits\",\"useBackgroundColor\":false,\"useNoData\":false,\"noDataString\":\"No data\",\"hideData\":false,\"hideLabel\":false,\"rounding\":1,\"valueFontSize\":24,\"labelFontSize\":14,\"thresholds\":[{\"from\":null,\"to\":null,\"color\":\"#16943E\"},{\"from\":null,\"to\":null,\"color\":\"#DFBE2E\"},{\"from\":null,\"to\":null,\"color\":\"#BF2121\"}],\"sparkline\":{\"show\":false,\"color\":\"#222D3B\"},\"gauge\":{\"show\":false,\"min\":0,\"max\":100,\"showThreshold\":false,\"showThresholdMarker\":false}},\"series\":{}}",
            "keepVisualSettingsConsistentWithParent": true,
            "panelType": "SumoSearchPanel",
            "queries": [
                {
                    "queryString": "_index=sumologic_volume dataPoints\n| where _sourceCategory=\"collector_metrics_volume\"\n| parse regex \"\\\"(?<collector>[^\\\"]+)\\\"\\:\\{\\\"dataPoints\\\"\\:(?<datapoints>\\d+)\\}\" multi\n| timeslice by {{timeslice}}\n|min(_messagetime) as f, max(_messagetime) as l , sum(datapoints) as datapoints by _timeslice\n| ((l - f)/(1000*60)) as duration_in_min\n| datapoints / duration_in_min as dpm\n| (dpm)/1000  * 3 * ( duration_in_min / ( 60 * 24))  as cr_metrics\n| sum(cr_metrics) as cr_metrics",
                    "queryType": "Logs",
                    "queryKey": "A",
                    "metricsQueryMode": null,
                    "metricsQueryData": null,
                    "tracesQueryData": null,
                    "parseMode": "Manual",
                    "timeSource": "Message"
                }
            ],
            "description": "",
            "timeRange": null,
            "coloringRules": null,
            "linkedDashboards": []
        },
        {
            "id": null,
            "key": "panel53A98BB8870DE848",
            "title": "Estimate Metric Credits Using DPM",
            "visualSettings": "{\"general\":{\"mode\":\"TextPanel\",\"type\":\"text\",\"displayType\":\"default\"},\"title\":{\"fontSize\":16},\"series\":{}}",
            "keepVisualSettingsConsistentWithParent": true,
            "panelType": "TextPanel",
            "text": ""
        },
        {
            "id": null,
            "key": "panel774314BABF501943",
            "title": "Infrequent Scan Credits Used",
            "visualSettings": "{\"general\":{\"mode\":\"TextPanel\",\"type\":\"text\",\"displayType\":\"default\"},\"title\":{\"fontSize\":16},\"series\":{}}",
            "keepVisualSettingsConsistentWithParent": true,
            "panelType": "TextPanel",
            "text": ""
        },
        {
            "id": null,
            "key": "panel32BB8380A63E9B41",
            "title": "Infrequent Scan Credits Consumed",
            "visualSettings": "{\"title\":{\"fontSize\":16},\"general\":{\"type\":\"line\",\"displayType\":\"default\",\"markerSize\":0,\"lineDashType\":\"solid\",\"markerType\":\"none\",\"lineThickness\":2,\"mode\":\"timeSeries\"},\"axes\":{\"axisX\":{\"showLabels\":true,\"title\":\"\",\"titleFontSize\":11,\"labelFontSize\":10},\"axisY\":{\"showLabels\":true,\"title\":\"\",\"titleFontSize\":11,\"labelFontSize\":12,\"logarithmic\":false,\"gridColor\":\"#dde4e9\"}},\"legend\":{\"enabled\":true,\"verticalAlign\":\"bottom\",\"fontSize\":12,\"maxHeight\":50,\"showAsTable\":false,\"wrap\":true},\"color\":{\"family\":\"scheme9\"},\"series\":{},\"overrides\":[{\"series\":[\"query_count\"],\"queries\":[],\"properties\":{\"axisYType\":\"secondary\",\"type\":\"column\"}}]}",
            "keepVisualSettingsConsistentWithParent": true,
            "panelType": "SumoSearchPanel",
            "queries": [
                {
                    "queryString": "_view=sumologic_search_usage_per_query analytics_tier = \"Infrequent\" !(user_name=*sumologic.com) !(status_message=\"Query Failed\")\t\n| fields data_scanned_bytes, query, is_aggregate, query_type, remote_ip, retrieved_message_count, scanned_message_count, scanned_partition_count, session_id, status_message, user_name\n|data_scanned_bytes / 1Gi as sizeInGB\n| sizeInGB * 0.016 as credits_consumed\n| timeslice 1d\n| sum (credits_consumed) as total_credits_consumed, count as query_count by _timeslice \n| fillmissing timeslice (1d)",
                    "queryType": "Logs",
                    "queryKey": "A",
                    "metricsQueryMode": null,
                    "metricsQueryData": null,
                    "tracesQueryData": null,
                    "parseMode": "Manual",
                    "timeSource": "Message"
                }
            ],
            "description": "",
            "timeRange": null,
            "coloringRules": null,
            "linkedDashboards": []
        },
        {
            "id": null,
            "key": "panel013E0607B2E87A41",
            "title": "Infrequent Scan Credits Consumed",
            "visualSettings": "{\"title\":{\"fontSize\":16},\"general\":{\"type\":\"svp\",\"displayType\":\"default\",\"mode\":\"singleValueMetrics\"},\"svp\":{\"option\":\"Average\",\"label\":\"credits\",\"useBackgroundColor\":false,\"useNoData\":false,\"noDataString\":\"0\",\"hideData\":false,\"hideLabel\":false,\"rounding\":1,\"valueFontSize\":24,\"labelFontSize\":14,\"thresholds\":[{\"from\":null,\"to\":null,\"color\":\"#16943E\"},{\"from\":null,\"to\":null,\"color\":\"#DFBE2E\"},{\"from\":null,\"to\":null,\"color\":\"#BF2121\"}],\"sparkline\":{\"show\":false,\"color\":\"#222D3B\"},\"gauge\":{\"show\":false,\"min\":0,\"max\":100,\"showThreshold\":false,\"showThresholdMarker\":false}},\"series\":{}}",
            "keepVisualSettingsConsistentWithParent": true,
            "panelType": "SumoSearchPanel",
            "queries": [
                {
                    "queryString": "_view=sumologic_search_usage_per_query analytics_tier = \"Infrequent\" !(user_name=*sumologic.com) !(status_message=\"Query Failed\")\t\n| fields data_scanned_bytes, query, is_aggregate, query_type, remote_ip, retrieved_message_count, scanned_message_count, scanned_partition_count, session_id, status_message, user_name\n|data_scanned_bytes / 1Gi as sizeInGB\n| sizeInGB * 0.016 as credits_consumed | sum(credits_consumed)\n",
                    "queryType": "Logs",
                    "queryKey": "A",
                    "metricsQueryMode": null,
                    "metricsQueryData": null,
                    "tracesQueryData": null,
                    "parseMode": "Manual",
                    "timeSource": "Message"
                }
            ],
            "description": "",
            "timeRange": null,
            "coloringRules": null,
            "linkedDashboards": []
        },
        {
            "id": null,
            "key": "panel2E9ED2749604AA4E",
            "title": "Estimate For Log Ingestion Credits",
            "visualSettings": "{\"general\":{\"mode\":\"TextPanel\",\"type\":\"text\",\"displayType\":\"default\"},\"title\":{\"fontSize\":16},\"series\":{}}",
            "keepVisualSettingsConsistentWithParent": true,
            "panelType": "TextPanel",
            "text": ""
        },
        {
            "id": null,
            "key": "panel2527AC6BBD9AF842",
            "title": "Estimated Lifetime Storage Credits for {{average_retention_days}} days retention",
            "visualSettings": "{\"general\":{\"mode\":\"TextPanel\",\"type\":\"text\",\"displayType\":\"default\"},\"title\":{\"fontSize\":16},\"series\":{},\"text\":{\"format\":\"markdown\",\"fontSize\":12}}",
            "keepVisualSettingsConsistentWithParent": true,
            "panelType": "TextPanel",
            "text": "This panel shows the GB ingested during the period per tier and the estimate for credits used to store those logs for the entire average_retention_days time.\n\nActual usage will vary as ingested volumes might fluctuate. \n\nFor new workloads (where full retention is not reached yet) or where usage is increasing/decresing this estimate will be less reliable.\n\nNote: cse_data (defined by cse_regex) are normalised data partitions written back to CIP by CSE. They are free to ingest but DO charge storage credits so are included here."
        },
        {
            "id": null,
            "key": "panel323647DE98CB5B4A",
            "title": "Estimated Period and Lifetime Storage Credit Use For {{average_retention_days}} Days Retention",
            "visualSettings": "{\"title\":{\"fontSize\":16},\"general\":{\"type\":\"table\",\"displayType\":\"default\",\"paginationPageSize\":100,\"fontSize\":12,\"mode\":\"distribution\",\"decimals\":0},\"series\":{}}",
            "keepVisualSettingsConsistentWithParent": true,
            "panelType": "SumoSearchPanel",
            "queries": [
                {
                    "queryString": "_index=sumologic_volume sizeInBytes \n_sourceCategory=view_volume\n\n| parse regex \"\\\"(?<view>[^\\\"]+)\\\"\\:\\{\\\"sizeInBytes\\\"\\:(?<bytes>\\d+),\\\"count\\\"\\:(?<count>\\d+)\\}\" multi\n| bytes / 1024 / 1024 / 1024 as gbytes\n\n| min(_messagetime) as f, max(_messagetime) as l,sum(gbytes) as gbytes by view\n| where gbytes > 0\n| \"continuous\" as tier\n| if(view matches /{{freq_regex}}/,\"frequent\",tier) as tier\n| if(view matches /{{infreq_regex}}/,\"infrequent\",tier) as tier\n| if (view matches /(?)CSE_[RS][ei]/,\"cse_data\",tier) as tier\n\n| view as rename_for_report\n| if(view matches \"_sumologic_report*\",\"saved_views\",view) as rename_for_report\n| if (view matches \"*sumologic*\",\"sumologic_internal\",rename_for_report) as rename_for_report\n\n| 0.0067 as cr_storage\n|  0.0015 as cr_infreq_storage\n\n| if (tier = \"infrequent\",cr_infreq_storage * gbytes,cr_storage * gbytes) as storage_credits\n| ( (l - f )/ (1000 * 60 * 60 * 24)) as duration_d\n| (storage_credits / duration_d) * {{average_retention_days}} as estimated_lifetime_storage_credits\n\n| max(duration_d) as period_days,sum(gbytes) as gbytes, sum(estimated_lifetime_storage_credits) as estimated_lifetime_storage_credits by tier\n| round(period_days,2) as period_days\n| round(gbytes,2) as gbytes_total\n| round(gbytes * ( 1/period_days),3) as gbytes_per_day\n| round(estimated_lifetime_storage_credits,2) as storage_credits_per_day_full_retention\n| round(estimated_lifetime_storage_credits /  {{average_retention_days}},3)  as storage_credits\n| fields -gbytes\n| fields tier, period_days,gbytes_total,gbytes_per_day,storage_credits,storage_credits_per_day_full_retention\n\n",
                    "queryType": "Logs",
                    "queryKey": "A",
                    "metricsQueryMode": null,
                    "metricsQueryData": null,
                    "tracesQueryData": null,
                    "parseMode": "Manual",
                    "timeSource": "Message"
                }
            ],
            "description": "",
            "timeRange": null,
            "coloringRules": null,
            "linkedDashboards": []
        },
        {
            "id": null,
            "key": "panelABC5F685A294E94D",
            "title": "Estimated Storage  Credits Per Day With {{average_retention_days}} Days Retention ",
            "visualSettings": "{\"title\":{\"fontSize\":16},\"general\":{\"type\":\"svp\",\"displayType\":\"default\",\"mode\":\"singleValueMetrics\"},\"svp\":{\"option\":\"Average\",\"label\":\"Credits\",\"useBackgroundColor\":false,\"useNoData\":false,\"noDataString\":\"0\",\"hideData\":false,\"hideLabel\":false,\"rounding\":0,\"valueFontSize\":24,\"labelFontSize\":14,\"thresholds\":[{\"from\":null,\"to\":null,\"color\":\"#16943E\"},{\"from\":null,\"to\":null,\"color\":\"#DFBE2E\"},{\"from\":null,\"to\":null,\"color\":\"#BF2121\"}],\"sparkline\":{\"show\":false,\"color\":\"#222D3B\"},\"gauge\":{\"show\":false,\"min\":0,\"max\":100,\"showThreshold\":false,\"showThresholdMarker\":false}},\"series\":{}}",
            "keepVisualSettingsConsistentWithParent": true,
            "panelType": "SumoSearchPanel",
            "queries": [
                {
                    "queryString": "_index=sumologic_volume sizeInBytes \n_sourceCategory=view_volume\n\n| parse regex \"\\\"(?<view>[^\\\"]+)\\\"\\:\\{\\\"sizeInBytes\\\"\\:(?<bytes>\\d+),\\\"count\\\"\\:(?<count>\\d+)\\}\" multi\n| bytes / 1024 / 1024 / 1024 as gbytes\n\n| min(_messagetime) as f, max(_messagetime) as l,sum(gbytes) as gbytes by view\n\n| \"continuous\" as tier\n| if(view matches /{{freq_regex}}/,\"frequent\",tier) as tier\n| if(view matches /{{infreq_regex}}/,\"infrequent\",tier) as tier\n| if (view matches /(?)CSE_[RS][ei]/,\"cse_data\",tier) as tier\n\n| view as rename_for_report\n| if(view matches \"_sumologic_report*\",\"saved_views\",view) as rename_for_report\n| if (view matches \"*sumologic*\",\"sumologic_internal\",rename_for_report) as rename_for_report\n\n| 0.0067 as cr_storage\n|  0.0015 as cr_infreq_storage\n\n| if (tier = \"infrequent\",cr_infreq_storage * gbytes,cr_storage * gbytes) as storage_credits\n| ( (l - f )/ (1000 * 60 * 60 * 24)) as duration_d\n| (storage_credits / duration_d) * {{average_retention_days}} as estimated_lifetime_storage_credits\n\n| max(duration_d) as period_days,sum(gbytes) as gbytes, sum(estimated_lifetime_storage_credits) as estimated_lifetime_storage_credits by tier\n| round(period_days,2) as period_days\n| round(gbytes,2) as gbytes_total\n| round(gbytes * ( 1/period_days),3) as gbytes_per_day\n| round(estimated_lifetime_storage_credits,2) as estimated_storage_credits_per_day_full_retention\n| round(estimated_lifetime_storage_credits /  {{average_retention_days}},3)  as storage_credits\n| fields -gbytes\n| fields tier, period_days,gbytes_total,gbytes_per_day,storage_credits,estimated_storage_credits_per_day_full_retention\n\n| sum( estimated_storage_credits_per_day_full_retention) as estimated_storage_credits_per_day_full_retention\n\n",
                    "queryType": "Logs",
                    "queryKey": "A",
                    "metricsQueryMode": null,
                    "metricsQueryData": null,
                    "tracesQueryData": null,
                    "parseMode": "Manual",
                    "timeSource": "Message"
                }
            ],
            "description": "",
            "timeRange": null,
            "coloringRules": null,
            "linkedDashboards": []
        },
        {
            "id": null,
            "key": "panelB0AACB67902B884D",
            "title": "Credits and GB Per Day",
            "visualSettings": "{\"title\":{\"fontSize\":14},\"general\":{\"type\":\"table\",\"displayType\":\"default\",\"paginationPageSize\":100,\"fontSize\":12,\"mode\":\"distribution\",\"decimals\":1},\"axes\":{\"axisX\":{\"titleFontSize\":12,\"labelFontSize\":12},\"axisY\":{\"titleFontSize\":12,\"labelFontSize\":12}},\"series\":{}}",
            "keepVisualSettingsConsistentWithParent": true,
            "panelType": "SumoSearchPanel",
            "queries": [
                {
                    "queryString": "_index=sumologic_volume sizeInBytes \n_sourceCategory=view_volume\n\n| parse regex \"\\\"(?<view>[^\\\"]+)\\\"\\:\\{\\\"sizeInBytes\\\"\\:(?<bytes>\\d+),\\\"count\\\"\\:(?<count>\\d+)\\}\" multi\n\n| if(view matches \"_sumologic_report*\",\"saved_views\",view) as view\n//| if(view matches \"*volume*\",\"internal\",view) as view\n| min(_messagetime) as s, max(_messagetime) as e , sum(bytes) as size_in_bytes by view\n| size_in_bytes / 1024 / 1024 / 1024 as gbytes\n| sum(gbytes) as gbytes by view,s,e\n| \"continuous\" as tier\n| if(view matches /{{freq_regex}}/,\"frequent\",tier) as tier\n| if(view matches /{{infreq_regex}}/,\"infrequent\",tier) as tier\n| if (view matches /(?)CSE_[RS][ei]/,\"cse_data\",tier) as tier\n| where !(tier = \"cse_data\")\n\n| if (tier = \"continuous\",gbytes * ((100 - {{cse_pct}})  /100),0) as continuous\n| if (tier = \"continuous\",gbytes * ({{cse_pct}}  /100),0) as cse\n| if (tier = \"frequent\", gbytes,0) as frequent\n| if (tier = \"infrequent\",gbytes,0) as infrequent\n\n\n| 20 as cr_cont\n| 25 as cr_cse\n| 9 as cr_freq\n| 0.4 as cr_infreq\n\n| if (tier = \"continuous\",cr_cont * gbytes * ((100 - {{cse_pct}})  /100),0) as cr_continuous\n| if (tier = \"continuous\",cr_cse * gbytes * ({{cse_pct}}  /100),0) as cr_cse\n| if (tier = \"frequent\",cr_freq * gbytes,0) as cr_frequent\n| if (tier = \"infrequent\",cr_infreq * gbytes,0) as cr_infrequent\n\n| min(s) as s, max(e) as e,sum(cr_continuous) as cr_cont, sum(cr_cse) as cr_cse, sum(cr_frequent) as cr_frequent,sum(cr_infrequent) as cr_infrequent,\nsum(continuous) as continuous, sum(cse) as cse,sum(frequent) as frequent, sum(infrequent) as infrequent\n\n| (e - s) / (1000 * 60 * 60 * 24) as days\n| continuous / days as continuous\n| cse / days as cse\n| frequent/ days as frequent\n| infrequent / days as infrequent\n\n| cr_cont / days as  cr_cont\n| cr_cse / days as cr_cse\n| cr_frequent/ days as cr_frequent\n| cr_infrequent / days as cr_infrequent\n| cr_cont + cr_cse + cr_frequent + cr_infrequent as cr_per_day\n| continuous + cse + frequent + infrequent as gb_per_day\n| cr_per_day / gb_per_day as CGPI\n| fields -s,e\n\n\n",
                    "queryType": "Logs",
                    "queryKey": "A",
                    "metricsQueryMode": null,
                    "metricsQueryData": null,
                    "tracesQueryData": null,
                    "parseMode": "Manual",
                    "timeSource": "Message"
                }
            ],
            "description": "",
            "timeRange": null,
            "coloringRules": null,
            "linkedDashboards": []
        },
        {
            "id": null,
            "key": "panelFD4EFA759646AB4C",
            "title": "Credits Per GB Ingested",
            "visualSettings": "{\"title\":{\"fontSize\":14},\"general\":{\"type\":\"svp\",\"displayType\":\"default\",\"mode\":\"singleValueMetrics\"},\"svp\":{\"option\":\"Average\",\"label\":\"CPGI\",\"useBackgroundColor\":false,\"useNoData\":false,\"noDataString\":\"No data\",\"hideData\":false,\"hideLabel\":false,\"rounding\":1,\"valueFontSize\":24,\"labelFontSize\":14,\"thresholds\":[{\"from\":0,\"to\":12,\"color\":\"#16943E\"},{\"from\":12,\"to\":18,\"color\":\"#DFBE2E\"},{\"from\":18,\"to\":100,\"color\":\"#BF2121\"}],\"sparkline\":{\"show\":false},\"gauge\":{\"show\":true,\"min\":0,\"max\":25}},\"series\":{}}",
            "keepVisualSettingsConsistentWithParent": true,
            "panelType": "SumoSearchPanel",
            "queries": [
                {
                    "queryString": "_index=sumologic_volume sizeInBytes \n_sourceCategory=view_volume\n\n| parse regex \"\\\"(?<view>[^\\\"]+)\\\"\\:\\{\\\"sizeInBytes\\\"\\:(?<bytes>\\d+),\\\"count\\\"\\:(?<count>\\d+)\\}\" multi\n\n| if(view matches \"_sumologic_report*\",\"saved_views\",view) as view\n//| if(view matches \"*volume*\",\"internal\",view) as view\n| min(_messagetime) as s, max(_messagetime) as e , sum(bytes) as size_in_bytes by view\n| size_in_bytes / 1024 / 1024 / 1024 as gbytes\n| sum(gbytes) as gbytes by view,s,e\n| \"continuous\" as tier\n| if(view matches /{{freq_regex}}/,\"frequent\",tier) as tier\n| if(view matches /{{infreq_regex}}/,\"infrequent\",tier) as tier\n| if (view matches /(?)CSE_[RS][ei]/,\"cse_data\",tier) as tier\n| sum(gbytes) as gbytes by tier\n\n| 20 as cr_cont\n| 25 as cr_cse\n| 9 as cr_freq\n| 0.4 as cr_infreq\n| cr_cont * gbytes * ((100 - {{cse_pct}} ) /100) as cr_cont\n| cr_cse * gbytes * ({{cse_pct}} /100)  as cr_cse\n| if (tier = \"continuous\", cr_cont+cr_cse ,0) as credits\n| if (tier = \"frequent\",cr_freq * gbytes,credits) as credits\n| if (tier = \"infrequent\",cr_infreq * gbytes,credits) as credits\n\n\n| if(tier  = \"frequent\",gbytes,0) as frequent\n| if (tier = \"continuous\",gbytes,0) as continuous\n| if(tier = \"infrequent\",gbytes,0) as infrequent\n| sum(continuous) as continuous,sum(frequent) as frequent, sum(infrequent) as infrequent\n\n| 20 as cr_cont\n| 25 as cr_cse\n| cr_cont * continuous * ((100 - {{cse_pct}} ) /100) as cr_cont\n| cr_cse * continuous * ({{cse_pct}} /100)  as cr_cse\n\n| ( cr_cont + cr_cse  + (frequent * 9) +  (infrequent * .4)  ) / (continuous + frequent + infrequent) as CPGI | avg(CPGI) as CPGI\n",
                    "queryType": "Logs",
                    "queryKey": "A",
                    "metricsQueryMode": null,
                    "metricsQueryData": null,
                    "tracesQueryData": null,
                    "parseMode": "Manual",
                    "timeSource": "Message"
                }
            ],
            "description": "",
            "timeRange": null,
            "coloringRules": null,
            "linkedDashboards": []
        },
        {
            "id": null,
            "key": "panel01F2578696E9D944",
            "title": "A) Annual ingest saved",
            "visualSettings": "{\"title\":{\"fontSize\":14},\"general\":{\"type\":\"svp\",\"displayType\":\"default\",\"mode\":\"singleValueMetrics\"},\"svp\":{\"option\":\"Average\",\"label\":\"credits\",\"useBackgroundColor\":false,\"useNoData\":false,\"noDataString\":\"No data\",\"hideData\":false,\"hideLabel\":false,\"rounding\":0,\"valueFontSize\":24,\"labelFontSize\":14,\"thresholds\":[{\"from\":0,\"to\":12,\"color\":\"#16943E\"},{\"from\":12,\"to\":18,\"color\":\"#DFBE2E\"},{\"from\":18,\"to\":100,\"color\":\"#BF2121\"}],\"sparkline\":{\"show\":false},\"gauge\":{\"show\":false,\"min\":0,\"max\":25}},\"series\":{}}",
            "keepVisualSettingsConsistentWithParent": true,
            "panelType": "SumoSearchPanel",
            "queries": [
                {
                    "queryString": "_index=sumologic_volume sizeInBytes \n_sourceCategory=view_volume\n\n| parse regex \"\\\"(?<view>[^\\\"]+)\\\"\\:\\{\\\"sizeInBytes\\\"\\:(?<bytes>\\d+),\\\"count\\\"\\:(?<count>\\d+)\\}\" multi\n\n| if(view matches \"_sumologic_report*\",\"saved_views\",view) as view\n//| if(view matches \"*volume*\",\"internal\",view) as view\n| min(_messagetime) as s, max(_messagetime) as e , sum(bytes) as size_in_bytes by view\n| size_in_bytes / 1024 / 1024 / 1024 as gbytes\n| min(s) as s, max(e) as e ,sum(gbytes) as gbytes by view,s,e\n| \"continuous\" as tier\n| if(view matches /{{freq_regex}}/,\"frequent\",tier) as tier\n| if(view matches /{{infreq_regex}}/,\"infrequent\",tier) as tier\n| if (view matches /(?)CSE_[RS][ei]/,\"cse_data\",tier) as tier\n| min(s) as s, max(e) as e ,sum(gbytes) as gbytes by tier\n| if(tier  = \"frequent\",gbytes,0) as frequent\n| if (tier = \"continuous\",gbytes,0) as continuous\n| if(tier = \"infrequent\",gbytes,0) as infrequent\n| min(s) as s, max(e) as e ,sum(continuous) as continuous,sum(frequent) as frequent, sum(infrequent) as infrequent\n| (e - s) / ( 1000 * 60 * 60 * 24) as range_days\n| ((( frequent + infrequent) * 20 - ((frequent * 9) + (infrequent * .4))) /range_days) * 365 as annual_ingest_credits_saved | fields annual_ingest_credits_saved",
                    "queryType": "Logs",
                    "queryKey": "A",
                    "metricsQueryMode": null,
                    "metricsQueryData": null,
                    "tracesQueryData": null,
                    "parseMode": "Manual",
                    "timeSource": "Message"
                }
            ],
            "description": "",
            "timeRange": null,
            "coloringRules": null,
            "linkedDashboards": []
        },
        {
            "id": null,
            "key": "panel668ACBF792B57842",
            "title": "B) Annual Infreq Scan Estimate",
            "visualSettings": "{\"title\":{\"fontSize\":16},\"general\":{\"type\":\"svp\",\"displayType\":\"default\",\"mode\":\"singleValueMetrics\"},\"svp\":{\"option\":\"Average\",\"label\":\"credits\",\"useBackgroundColor\":false,\"useNoData\":false,\"noDataString\":\"0\",\"hideData\":false,\"hideLabel\":false,\"rounding\":1,\"valueFontSize\":24,\"labelFontSize\":14,\"thresholds\":[{\"from\":null,\"to\":null,\"color\":\"#16943E\"},{\"from\":null,\"to\":null,\"color\":\"#DFBE2E\"},{\"from\":null,\"to\":null,\"color\":\"#BF2121\"}],\"sparkline\":{\"show\":false,\"color\":\"#222D3B\"},\"gauge\":{\"show\":false,\"min\":0,\"max\":100,\"showThreshold\":false,\"showThresholdMarker\":false}},\"series\":{}}",
            "keepVisualSettingsConsistentWithParent": true,
            "panelType": "SumoSearchPanel",
            "queries": [
                {
                    "queryString": "_view=sumologic_search_usage_per_query analytics_tier = \"Infrequent\" !(user_name=*sumologic.com) !(status_message=\"Query Failed\")\t\n| fields data_scanned_bytes, query, is_aggregate, query_type, remote_ip, retrieved_message_count, scanned_message_count, scanned_partition_count, session_id, status_message, user_name\n|data_scanned_bytes / 1Gi as sizeInGB\n| (sizeInGB * 0.016 ) as credits_consumed    | sum(credits_consumed)\n| credits_consumed /7  * 365 as credits_consumed\n",
                    "queryType": "Logs",
                    "queryKey": "A",
                    "metricsQueryMode": null,
                    "metricsQueryData": null,
                    "tracesQueryData": null,
                    "parseMode": "Manual",
                    "timeSource": "Message"
                }
            ],
            "description": "",
            "timeRange": null,
            "coloringRules": null,
            "linkedDashboards": []
        },
        {
            "id": null,
            "key": "panel0F0DA71B810C494A",
            "title": "CIP vs CSE Routing %",
            "visualSettings": "{\"title\":{\"fontSize\":14},\"general\":{\"type\":\"table\",\"displayType\":\"default\",\"paginationPageSize\":100,\"fontSize\":12,\"mode\":\"distribution\",\"decimals\":null},\"axes\":{\"axisX\":{\"titleFontSize\":12,\"labelFontSize\":12},\"axisY\":{\"titleFontSize\":12,\"labelFontSize\":12}},\"series\":{}}",
            "keepVisualSettingsConsistentWithParent": true,
            "panelType": "SumoSearchPanel",
            "queries": [
                {
                    "queryString": "_sourceCategory=* not _sourcecategory=asoc/* not _sourcecategory=cse/* //AND (AND _messageid=*0 or _messageid=*5)\n| _view as index\n| if (isempty(_siemforward),\"CIP\",\"CSE\") as forwarding\n| sum(_size) as bytes, count_distinct(index) as partitions, count_distinct(_sourcecategory) as categories by forwarding\n| bytes / 1024 /1024 as mb | total mb as tmb | (mb / tmb) * 100  as percent \n| fields forwarding, mb,categories,percent \n| if (forwarding = \"CIP\",20,25) as %\"cr/gb\"\n| round(percent,1) as percent\n| round(mb) as mb\n",
                    "queryType": "Logs",
                    "queryKey": "A",
                    "metricsQueryMode": null,
                    "metricsQueryData": null,
                    "tracesQueryData": null,
                    "parseMode": "Manual",
                    "timeSource": "Message"
                }
            ],
            "description": "",
            "timeRange": {
                "type": "BeginBoundedTimeRange",
                "from": {
                    "type": "RelativeTimeRangeBoundary",
                    "relativeTime": "-1h"
                },
                "to": null
            },
            "coloringRules": null,
            "linkedDashboards": []
        },
        {
            "id": null,
            "key": "panelB6F0E7878F04384E",
            "title": "Credits Savings (A - B)",
            "visualSettings": "{\"general\":{\"mode\":\"TextPanel\",\"type\":\"text\",\"displayType\":\"default\"},\"title\":{\"fontSize\":16},\"series\":{},\"text\":{\"fontSize\":14}}",
            "keepVisualSettingsConsistentWithParent": true,
            "panelType": "TextPanel",
            "text": "Subtract B from A to show annual estimated savings from your data tiering."
        },
        {
            "id": null,
            "key": "panelAFB174FABBC89B4D",
            "title": "CIP vs CSE Credits Estimate",
            "visualSettings": "{\"general\":{\"mode\":\"TextPanel\",\"type\":\"text\",\"displayType\":\"default\"},\"title\":{\"fontSize\":16},\"series\":{},\"text\":{\"fontSize\":14}}",
            "keepVisualSettingsConsistentWithParent": true,
            "panelType": "TextPanel",
            "text": "Use the % value for CSE in the cse_pct parameter to estimate cse (25) vs cip (20) ingest credits. If CSE is not used use the value 0."
        },
        {
            "id": null,
            "key": "panelF2060CD3BDA43842",
            "title": "CSE Records/Signals",
            "visualSettings": "{\"title\":{\"fontSize\":16},\"general\":{\"type\":\"column\",\"displayType\":\"stacked\",\"fillOpacity\":1,\"mode\":\"timeSeries\"},\"axes\":{\"axisX\":{\"showLabels\":true,\"title\":\"\",\"titleFontSize\":11,\"labelFontSize\":10},\"axisY\":{\"showLabels\":true,\"title\":\"\",\"titleFontSize\":11,\"labelFontSize\":12,\"logarithmic\":false,\"gridColor\":\"#dde4e9\"}},\"legend\":{\"enabled\":true,\"verticalAlign\":\"bottom\",\"fontSize\":12,\"maxHeight\":50,\"showAsTable\":false,\"wrap\":true},\"color\":{\"family\":\"scheme9\"},\"overrides\":[],\"series\":{}}",
            "keepVisualSettingsConsistentWithParent": true,
            "panelType": "SumoSearchPanel",
            "queries": [
                {
                    "queryString": "_index=sumologic_volume sizeInBytes \n_sourceCategory=view_volume\n\n| parse regex \"\\\"(?<view>[^\\\"]+)\\\"\\:\\{\\\"sizeInBytes\\\"\\:(?<bytes>\\d+),\\\"count\\\"\\:(?<count>\\d+)\\}\" multi\n\n| if(view matches \"_sumologic_report*\",\"saved_views\",view) as view\n//| if(view matches \"*volume*\",\"internal\",view) as view\n| timeslice by {{timeslice}} \n\n| sum(bytes) as size_in_bytes by view,_timeslice\n| size_in_bytes / 1024 / 1024 / 1024 as gbytes\n| sum(gbytes) as gbytes by view,_timeslice\n\n| \"continuous\" as tier\n| if(view matches /{{freq_regex}}/,\"frequent\",tier) as tier\n| if(view matches /{{infreq_regex}}/,\"infrequent\",tier) as tier\n| if (view matches /(?)CSE_[RS][ei]/,\"cse_data\",tier) as tier\n\n| where tier = \"cse_data\"\n| view as index\n| if (index matches \"*sumologic*\",\"sumologic_internal\",index) as index\n|  sum(gbytes) as gbytes by index,_timeslice\n| transpose row _timeslice column index\n",
                    "queryType": "Logs",
                    "queryKey": "A",
                    "metricsQueryMode": null,
                    "metricsQueryData": null,
                    "tracesQueryData": null,
                    "parseMode": "Manual",
                    "timeSource": "Message"
                }
            ],
            "description": "",
            "timeRange": null,
            "coloringRules": null,
            "linkedDashboards": []
        }
    ],
    "variables": [
        {
            "id": "DDE21324866E7042",
            "name": "freq_regex",
            "displayName": "freq_regex",
            "defaultValue": "_freq",
            "sourceDefinition": {
                "variableSourceType": "CsvVariableSourceDefinition",
                "values": "_freq"
            },
            "allowMultiSelect": false,
            "includeAllOption": false,
            "hideFromUI": false
        },
        {
            "id": "4855D17F20E4590F",
            "name": "infreq_regex",
            "displayName": "infreq_regex",
            "defaultValue": "infrequent",
            "sourceDefinition": {
                "variableSourceType": "CsvVariableSourceDefinition",
                "values": "infrequent|"
            },
            "allowMultiSelect": false,
            "includeAllOption": false,
            "hideFromUI": false
        },
        {
            "id": "54F8345ACA0BEFF5",
            "name": "timeslice",
            "displayName": null,
            "defaultValue": "1d",
            "sourceDefinition": {
                "variableSourceType": "CsvVariableSourceDefinition",
                "values": "1h,1d,15m"
            },
            "allowMultiSelect": false,
            "includeAllOption": false,
            "hideFromUI": false
        },
        {
            "id": "F6C2D2C9031CB403",
            "name": "average_retention_days",
            "displayName": "average_retention_days",
            "defaultValue": "30",
            "sourceDefinition": {
                "variableSourceType": "CsvVariableSourceDefinition",
                "values": "30,90,365,390"
            },
            "allowMultiSelect": false,
            "includeAllOption": false,
            "hideFromUI": false
        },
        {
            "id": "97CBDB7BBB82825A",
            "name": "cse_regex",
            "displayName": "cse_regex",
            "defaultValue": "cse_|asoc",
            "sourceDefinition": {
                "variableSourceType": "CsvVariableSourceDefinition",
                "values": "cse_|asoc"
            },
            "allowMultiSelect": false,
            "includeAllOption": false,
            "hideFromUI": false
        },
        {
            "id": "BB96DFF2B0193888",
            "name": "cse_pct",
            "displayName": "cse_pct",
            "defaultValue": "0",
            "sourceDefinition": {
                "variableSourceType": "CsvVariableSourceDefinition",
                "values": "15,20,25,30,35,40,45,50,55,65,70,75,80,85,90,95,99"
            },
            "allowMultiSelect": false,
            "includeAllOption": false,
            "hideFromUI": false
        }
    ],
    "coloringRules": []
}