{
  "id": "q0373",
  "hash": "34112516b5d7",
  "queryType": "Traces",
  "queryMode": "Traces",
  "query": "",
  "queryParameters": [],
  "viewerType": "traceListTable",
  "metricsQueryData": null,
  "tracesQueryData": {
    "filters": [
      {
        "type": "FieldDescriptor",
        "operator": "=",
        "field": "service",
        "value": "{{service}}",
        "valueType": "StringTracingValue",
        "target": "any span"
      },
      {
        "type": "FieldDescriptor",
        "operator": "=",
        "field": "deployment.environment",
        "value": "{{environment}}",
        "valueType": "StringTracingValue",
        "target": "any span"
      },
      {
        "type": "FieldDescriptor",
        "operator": "=",
        "field": "db.system",
        "value": "{{db_system}}",
        "valueType": "StringTracingValue",
        "target": "any span"
      },
      {
        "type": "FieldDescriptor",
        "operator": "=",
        "field": "db.name",
        "value": "{{db_name}}",
        "valueType": "StringTracingValue",
        "target": "any span"
      }
    ]
  },
  "sources": [
    {
      "file": "apps/Tracing and Spans/tracing - database operations.json",
      "objectType": "Dashboard",
      "folder": null,
      "dashboardName": "Tracing - Database Operations",
      "dashboardDescription": "",
      "panelTitle": "Traces With db_system",
      "panelType": "TracesListPanel",
      "panelKey": "panelPANE-3A146F83908B0A42",
      "visualization": "traceListTable",
      "visualSettingsRaw": "{\"general\":{\"mode\":\"traceList\",\"type\":\"traceListTable\",\"displayType\":\"default\"},\"title\":{\"fontSize\":14},\"displaySettings\":{\"chartType\":\"traceList\"},\"legend\":{\"enabled\":false}}",
      "rowContext": [
        "Other Details"
      ],
      "variables": [
        {
          "name": "keywords",
          "defaultValue": "*",
          "values": "any keyword string",
          "allowMultiSelect": false
        },
        {
          "name": "environment",
          "defaultValue": "prod",
          "values": null,
          "allowMultiSelect": false
        },
        {
          "name": "service",
          "defaultValue": "*",
          "values": null,
          "allowMultiSelect": false
        },
        {
          "name": "db_name",
          "defaultValue": "*",
          "values": null,
          "allowMultiSelect": false
        },
        {
          "name": "db_system",
          "defaultValue": "*",
          "values": null,
          "allowMultiSelect": false
        }
      ]
    }
  ]
}