{
  "id": "q1577",
  "hash": "cc84c1b02092",
  "queryType": "Metrics",
  "queryMode": "Metrics-Advanced",
  "query": "metric=kube_pod_container_status_restarts_total cluster={{cluster}} namespace={{namespace}} deployment={{deployment}} | quantize to {{quantization_interval}} | sum | delta | eval max(_value, 0)",
  "queryParameters": [
    {
      "autoComplete": {
        "type": "SKIP_AUTOCOMPLETE",
        "autoCompleteKey": "",
        "autoCompleteValues": [],
        "lookupMetaData": {}
      },
      "name": "cluster",
      "description": "",
      "dataType": "ANY",
      "value": ""
    },
    {
      "autoComplete": {
        "type": "SKIP_AUTOCOMPLETE",
        "autoCompleteKey": "",
        "autoCompleteValues": [],
        "lookupMetaData": {}
      },
      "name": "namespace",
      "description": "",
      "dataType": "ANY",
      "value": "*"
    },
    {
      "autoComplete": {
        "type": "SKIP_AUTOCOMPLETE",
        "autoCompleteKey": "",
        "autoCompleteValues": [],
        "lookupMetaData": {}
      },
      "name": "deployment",
      "description": "",
      "dataType": "ANY",
      "value": ""
    },
    {
      "autoComplete": {
        "type": "SKIP_AUTOCOMPLETE",
        "autoCompleteKey": "",
        "autoCompleteValues": [],
        "lookupMetaData": {}
      },
      "name": "quantization_interval",
      "description": "1m,5m,15m",
      "dataType": "ANY",
      "value": "1m"
    }
  ],
  "viewerType": "timeSeries",
  "metricsQueryData": null,
  "tracesQueryData": null,
  "sources": [
    {
      "file": "apps/kubernetes/kubernetes_collection_app_versions/kubernetes_app_20250416.json",
      "objectType": "Dashboard",
      "folder": "Kubernetes",
      "dashboardName": "Kubernetes - Deployment - Overview",
      "dashboardDescription": "The Kubernetes - Deployment Overview dashboard provides high-level insights into the health and performance of your Kubernetes deployments.",
      "panelTitle": "Pods Running vs Restarts",
      "panelType": "SumoSearchPanel",
      "panelKey": "panelpane-3432a6259a7db840",
      "visualization": "timeSeries",
      "visualSettingsRaw": "{\"general\":{\"mode\":\"timeSeries\",\"lineThickness\":2},\"hiddenQueryKeys\":[\"B\",\"A\"],\"color\":{\"family\":\"scheme7\"},\"series\":{},\"axes\":{\"axisY\":{\"gridColor\":\"#e9ebf1\"}}}",
      "rowContext": [
        "Note: Selecting cluster name, namespace and deployment is mandatory for dashboard to work"
      ],
      "variables": [
        {
          "name": "cluster",
          "defaultValue": "",
          "values": null,
          "allowMultiSelect": false
        },
        {
          "name": "namespace",
          "defaultValue": "*",
          "values": null,
          "allowMultiSelect": false
        },
        {
          "name": "deployment",
          "defaultValue": null,
          "values": null,
          "allowMultiSelect": false
        },
        {
          "name": "quantization_interval",
          "defaultValue": "1m",
          "values": "1m,5m,15m",
          "allowMultiSelect": false
        }
      ]
    }
  ]
}